DESCRIPTION.rst
MANIFEST.in
README.rst
setup.py
mclearn/__init__.py
mclearn/active.py
mclearn/classifier.py
mclearn/heuristics.py
mclearn/performance.py
mclearn/photometry.py
mclearn/preprocessing.py
mclearn/tools.py
mclearn/viz.py
mclearn.egg-info/PKG-INFO
mclearn.egg-info/SOURCES.txt
mclearn.egg-info/dependency_links.txt
mclearn.egg-info/pbr.json
mclearn.egg-info/requires.txt
mclearn.egg-info/top_level.txt
mclearn/knfst/__init__.py
mclearn/knfst/knfst.py
mclearn/knfst/learn_multiClassNovelty_knfst.py
mclearn/tests/__init__.py
mclearn/tests/datasets.py
mclearn/tests/test_active.py
mclearn/tests/test_mclearn.py
mclearn/tests/test_photometry.py
mclearn/tests/test_preprocessing.py
mclearn/tests/test_tools.py
mclearn/tests/data/glass.csv
mclearn/tests/data/sdss_tiny.csv
mclearn/tests/data/wine.csv
mclearn/tests/data/filters/g.dat
mclearn/tests/data/filters/i.dat
mclearn/tests/data/filters/r.dat
mclearn/tests/data/filters/u.dat
mclearn/tests/data/filters/z.dat
mclearn/tests/data/spectra/1732526_nic_002.ascii