Metadata-Version: 1.1
Name: mclearn
Version: 0.1.6
Summary: Active learning algorithms with application in astronomy.
Home-page: https://github.com/alasdairtran/mclearn
Author: Alasdair Tran
Author-email: alasdair.tran@gmail.com
License: BSD
Keywords: active learning astronomy classficiation
Platform: UNKNOWN
Classifier: Development Status :: 3 - Alpha
Classifier: Intended Audience :: Science/Research
Classifier: Topic :: Scientific/Engineering
Classifier: License :: OSI Approved :: BSD License
Classifier: Programming Language :: Python :: 3.4
